djhubspot/__init__.py
djhubspot/admin.py
djhubspot/apps.py
djhubspot/compat.py
djhubspot/models.py
djhubspot/views.py
dj_hubspot-0.1.1.dist-info/LICENSE
dj_hubspot-0.1.1.dist-info/WHEEL
dj_hubspot-0.1.1.dist-info/METADATA
dj_hubspot-0.1.1.dist-info/RECORD
